gnat-0.2.0.dist-info/top_level.txt
gnat-0.2.0.dist-info/RECORD
gnat-0.2.0.dist-info/METADATA
gnat-0.2.0.dist-info/WHEEL
gnat/_gnat.cpython-310-i386-linux-gnu.so
gnat/__init__.py
tests/test.py
tests/__init__.py
tests/test_online.py
tests/comparison.py
gnat.libs/libgcc_s-8b50eaaa.so.1
gnat.libs/libstdc++-8baf04f9.so.6.0.28
